codefellows/__init__.py
codefellows/dsa/binary_tree.py
codefellows/dsa/graph.py
codefellows/dsa/linked_list.py
codefellows/dsa/queue.py
codefellows/dsa/stack.py
codefellows-0.6.0.dist-info/WHEEL
codefellows-0.6.0.dist-info/METADATA
codefellows-0.6.0.dist-info/RECORD
