Metadata-Version: 2.1
Name: codefellows
Version: 0.6.0
Summary: Commonly needed Python modules
Author: codefellows
Author-email: jb@codefellows.com
Requires-Python: >=3.8,<4.0
Classifier: Programming Language :: Python :: 3
Classifier: Programming Language :: Python :: 3.8
Classifier: Programming Language :: Python :: 3.9
